snapthing/__init__.py
snapthing/cli.py
snapthing/config.py
snapthing/eventhandling.py
snapthing/keys.py
snapthing/platforms.py
snapthing/snap.py
snapthing-0.1.0.dist-info/METADATA
snapthing-0.1.0.dist-info/WHEEL
snapthing-0.1.0.dist-info/entry_points.txt
snapthing-0.1.0.dist-info/top_level.txt
snapthing-0.1.0.dist-info/RECORD
