Metadata-Version: 2.2
Name: snapthing
Version: 0.1.0
Summary: A tool for taking screenshots
Home-page: https://snap.dotle.ca
Author: Blake Smith
Author-email: blake@dotle.ca
Classifier: Programming Language :: Python :: 3
Classifier: License :: OSI Approved :: MIT License
Classifier: Operating System :: OS Independent
Requires-Python: >=3.6
Requires-Dist: pillow==11.1.0
Requires-Dist: PyAutoGUI==0.9.54
Dynamic: author
Dynamic: author-email
Dynamic: classifier
Dynamic: description
Dynamic: description-content-type
Dynamic: home-page
Dynamic: requires-dist
Dynamic: requires-python
Dynamic: summary
